AUTHORS.rst
CHANGELOG.rst
LICENSE
MANIFEST.in
README.rst
setup.py
chart/__init__.py
chart/admin.py
chart/generator.py
chart/models.py
chart/tests.py
chart/urls.py
chart/fixtures/photosizes.json
chart/management/__init__.py
chart/management/__init__.pyc
chart/management/commands/__init__.py
chart/management/commands/chartupdate.py
chart/templates/basic/chart/inclusion_tags/chart_detail.html
chart/templates/web/chart/inclusion_tags/chart_detail.html
jmbo_chart.egg-info/PKG-INFO
jmbo_chart.egg-info/SOURCES.txt
jmbo_chart.egg-info/dependency_links.txt
jmbo_chart.egg-info/not-zip-safe
jmbo_chart.egg-info/requires.txt
jmbo_chart.egg-info/top_level.txt